pysxgeo/sxgeo.py
pysxgeo/opts.py
pysxgeo/__init__.py
pysxgeo-0.0.3.dist-info/top_level.txt
pysxgeo-0.0.3.dist-info/RECORD
pysxgeo-0.0.3.dist-info/metadata.json
pysxgeo-0.0.3.dist-info/METADATA
pysxgeo-0.0.3.dist-info/DESCRIPTION.rst
pysxgeo-0.0.3.dist-info/WHEEL
