Metadata-Version: 2.0
Name: pysxgeo
Version: 0.0.3
Summary: This API provides access to Sypex Geo 2.2 databases. The databases available from https://sypexgeo.net/ 
Home-page: https://bitbucket.org/niklak/pysxgeo/
Author: Nikolay Gumanov
Author-email: morgenpurple@gmail.com
License: UNKNOWN
Keywords: geolocation
Platform: UNKNOWN
Classifier: Development Status :: 5 - Production/Stable
Classifier: Environment :: Web Environment
Classifier: Intended Audience :: Developers
Classifier: Intended Audience :: System Administrators
Classifier: Operating System :: OS Independent
Classifier: Programming Language :: Python :: 3
Classifier: Programming Language :: Python :: 3.2
Classifier: Programming Language :: Python :: 3.3
Classifier: Programming Language :: Python :: 3.4
